{
  "url": "https://api.github.com/repos/kemu3007/portal/issues/13",
  "repository_url": "https://api.github.com/repos/kemu3007/portal",
  "labels_url": "https://api.github.com/repos/kemu3007/portal/issues/13/labels{/name}",
  "comments_url": "https://api.github.com/repos/kemu3007/portal/issues/13/comments",
  "events_url": "https://api.github.com/repos/kemu3007/portal/issues/13/events",
  "html_url": "https://github.com/kemu3007/portal/issues/13",
  "id": 1167241988,
  "node_id": "I_kwDOG7qoq85FkrME",
  "number": 13,
  "title": "在用GitHub页面部署的SPA中显示OGPs(spirited)。",
  "user": {
    "login": "kemu3007",
    "id": 29157528,
    "node_id": "MDQ6VXNlcjI5MTU3NTI4",
    "avatar_url": "https://avatars.githubusercontent.com/u/29157528?v=4",
    "gravatar_id": "",
    "url": "https://api.github.com/users/kemu3007",
    "html_url": "https://github.com/kemu3007",
    "followers_url": "https://api.github.com/users/kemu3007/followers",
    "following_url": "https://api.github.com/users/kemu3007/following{/other_user}",
    "gists_url": "https://api.github.com/users/kemu3007/gists{/gist_id}",
    "starred_url": "https://api.github.com/users/kemu3007/starred{/owner}{/repo}",
    "subscriptions_url": "https://api.github.com/users/kemu3007/subscriptions",
    "organizations_url": "https://api.github.com/users/kemu3007/orgs",
    "repos_url": "https://api.github.com/users/kemu3007/repos",
    "events_url": "https://api.github.com/users/kemu3007/events{/privacy}",
    "received_events_url": "https://api.github.com/users/kemu3007/received_events",
    "type": "User",
    "site_admin": false
  },
  "labels": [
    {
      "id": 3898939400,
      "node_id": "LA_kwDOG7qoq87oZRgI",
      "url": "https://api.github.com/repos/kemu3007/portal/labels/article",
      "name": "article",
      "color": "C200E5",
      "default": false,
      "description": ""
    },
    {
      "id": 3900074882,
      "node_id": "LA_kwDOG7qoq87odmuC",
      "url": "https://api.github.com/repos/kemu3007/portal/labels/Angular",
      "name": "Angular",
      "color": "D93F0B",
      "default": false,
      "description": ""
    }
  ],
  "state": "open",
  "locked": false,
  "assignee": null,
  "assignees": [],
  "milestone": null,
  "comments": 0,
  "created_at": "2022-03-12T09:56:24Z",
  "updated_at": "2022-03-12T14:33:09Z",
  "closed_at": null,
  "author_association": "OWNER",
  "active_lock_reason": null,
  "body": "例如，如果你通常部署一个SPA，OGP将不会在twitter上显示。\n\n这是由于检索OGP的机器人没有执行js，而且由于SPA，相关链接没有静态HTML文件。\n\n出于这个原因，lambda和其他方法通常用于为机器人显示页面，而其他访问被发送到S3。\n\n然而，这次我们想只用GitHub页面来完成这个过程，而不需要投入那么多精力，所以我们寻求一个解决方案。\n\n\n###解决方案。\n\n_如果你没有，为什么不直接添加一个页面？\n\n这一次，相关的链接目录（本例中为 \"src/blog\"）被添加到angular.json的assets中，并在构建时被保留。\n\n该页面是通过在部署时运行Action中的Python脚本来创建的，该脚本生成了一个如下形式的文件。\n\n```\nsrc/blog/index.html\nsrc/blog/<:id>/index.html\n```\n\n见：https://github.com/kemu3007/portal/blob/master/create_pages.py\n\n首先准备好HTML的内容，将标题、图片和描述的内容修改为你想在相关页面上显示的内容，然后将HTML文件保存在与页面上的链接相匹配的目录中。然后，HTML文件被保存在与页面上的链接相匹配的目录中。\n\n当你踩到直接链接时，这将把你带到只包含静态OGP的HTML，而不需要通过SPA，这样你就可以过渡到Angular应用程序存在于这个页面中的根链接，把当前路径作为查询参数传递，用内部链接过渡。\n\n注意，如果你在app- component中这样做，`route.snapshot.queryParams`将是空的，因为它不在router- outlet里面。\n\nbot: 链接 - > `OGP- only HTML`。\n访客：链接 - > `OGP- only HTML` - > `Angular Application`。\n\n一旦过渡到应用程序，所有后续的过渡都由内部链接处理，所以不存在过渡问题。\n\n\n### 印象。\n\n这是一个简单易行的方法，但需要花费一点时间。\n\n我以一种激昂的方式解决了OGP，所以如果你问我是否会在工作中这样做，我不会。 但这是我的个人博客，所以我很乐意这样做。\n\n我觉得我对SEO一窍不通，哪怕是一点点，所以如果你有更好的方法，请在评论中告诉我。",
  "reactions": {
    "url": "https://api.github.com/repos/kemu3007/portal/issues/13/reactions",
    "total_count": 0,
    "+1": 0,
    "-1": 0,
    "laugh": 0,
    "hooray": 0,
    "confused": 0,
    "heart": 0,
    "rocket": 0,
    "eyes": 0
  },
  "timeline_url": "https://api.github.com/repos/kemu3007/portal/issues/13/timeline",
  "performed_via_github_app": null,
  "state_reason": null
}
