{"url": "https://api.github.com/repos/kemu3007/portal/issues/43", "repository_url": "https://api.github.com/repos/kemu3007/portal", "labels_url": "https://api.github.com/repos/kemu3007/portal/issues/43/labels{/name}", "comments_url": "https://api.github.com/repos/kemu3007/portal/issues/43/comments", "events_url": "https://api.github.com/repos/kemu3007/portal/issues/43/events", "html_url": "https://github.com/kemu3007/portal/issues/43", "id": 1228774700, "node_id": "I_kwDOG7qoq85JPZ0s", "number": 43, "title": "使用MacOS Clamav进行病毒扫描", "user": {"login": "kemu3007", "id": 29157528, "node_id": "MDQ6VXNlcjI5MTU3NTI4", "avatar_url": "https://avatars.githubusercontent.com/u/29157528?v=4", "gravatar_id": "", "url": "https://api.github.com/users/kemu3007", "html_url": "https://github.com/kemu3007", "followers_url": "https://api.github.com/users/kemu3007/followers", "following_url": "https://api.github.com/users/kemu3007/following{/other_user}", "gists_url": "https://api.github.com/users/kemu3007/gists{/gist_id}", "starred_url": "https://api.github.com/users/kemu3007/starred{/owner}{/repo}", "subscriptions_url": "https://api.github.com/users/kemu3007/subscriptions", "organizations_url": "https://api.github.com/users/kemu3007/orgs", "repos_url": "https://api.github.com/users/kemu3007/repos", "events_url": "https://api.github.com/users/kemu3007/events{/privacy}", "received_events_url": "https://api.github.com/users/kemu3007/received_events", "type": "User", "site_admin": false}, "labels": [{"id": 3898939400, "node_id": "LA_kwDOG7qoq87oZRgI", "url": "https://api.github.com/repos/kemu3007/portal/labels/article", "name": "article", "color": "C200E5", "default": false, "description": ""}, {"id": 3900082041, "node_id": "LA_kwDOG7qoq87odod5", "url": "https://api.github.com/repos/kemu3007/portal/labels/Utils", "name": "Utils", "color": "170627", "default": false, "description": ""}], "state": "open", "locked": false, "assignee": null, "assignees": [], "milestone": null, "comments": 0, "created_at": "2022-05-08T02:31:49Z", "updated_at": "2022-05-08T03:19:55Z", "closed_at": null, "author_association": "OWNER", "active_lock_reason": null, "body": "我不想成为Clamav居民，但我想使用常规的完整扫描来确保安全，因此我将介绍如何做。\r\n\r\n＃＃ 环境\r\n\r\nM1 MacBook Air\r\n\r\n＃＃ 安装\r\n\r\n使用自制。\r\n\r\n````bash\r\n$ BREW安装Clamav\r\n````````\r\n\r\n##更新漏洞/病毒模式\r\n\r\n###配置文件的准备\r\n\r\n使用默认情况下准备的内容。\r\n\r\n````bash\r\n美元\r\n````````\r\n\r\n从`/opt/homebrew/etc/clamav/frordclam.conf`消除示例行。\r\n\r\n\r\n###更新漏洞/病毒模式\r\n\r\n\r\n````bash\r\n$新生\r\n````````\r\n\r\n##运行扫描\r\n\r\n扫描主目录。\r\n\r\n````bash\r\n$ CALMSCAN〜/  - 征收 - 感染\r\n````````\r\n\r\n` -  recursive`：递归验证文件的内容。\r\n`-Infected`：将输出内容限制在病毒文件中。\r\n\r\n##扫描结果\r\n\r\n````bash\r\n----------扫描摘要--------------------------------------------------------------------------\r\n已知病毒：8615816\r\n发动机版本：0.105.0\r\n扫描目录：96767\r\n扫描文件：574546\r\n受感染文件：0\r\n总错误：102\r\n数据扫描：33283.79 MB\r\n数据读数：101097.09 MB（比率0.33：1）\r\n时间：2366.628秒（39 m 26 s）\r\n开始日期：2022：05：08 10：42：33\r\n结束日期：2022：05：08 11：22：00\r\n````````\r\n\r\n##定期执行\r\n\r\n````bash\r\n$ crontab -e\r\n````````\r\n\r\n图案更新在周日/主目录扫描执行时间为0:00\r\n\r\n````bash\r\n0 0 * * 0新生和clamscan/users/kemu/ - 递归 - 感染\r\n````````", "reactions": {"url": "https://api.github.com/repos/kemu3007/portal/issues/43/reactions", "total_count": 0, "+1": 0, "-1": 0, "laugh": 0, "hooray": 0, "confused": 0, "heart": 0, "rocket": 0, "eyes": 0}, "timeline_url": "https://api.github.com/repos/kemu3007/portal/issues/43/timeline", "performed_via_github_app": null, "state_reason": null}