{"url": "https://api.github.com/repos/kemu3007/portal/issues/39", "repository_url": "https://api.github.com/repos/kemu3007/portal", "labels_url": "https://api.github.com/repos/kemu3007/portal/issues/39/labels{/name}", "comments_url": "https://api.github.com/repos/kemu3007/portal/issues/39/comments", "events_url": "https://api.github.com/repos/kemu3007/portal/issues/39/events", "html_url": "https://github.com/kemu3007/portal/issues/39", "id": 1221980066, "node_id": "I_kwDOG7qoq85I1e-i", "number": 39, "title": "\u30b9\u30fc\u30d1\u30fc\u30ed\u30dc\u30c3\u30c8\u9b422022\uff5estage terra\uff5e\u884c\u3063\u3066\u304d\u307e\u3057\u305f", "user": {"login": "kemu3007", "id": 29157528, "node_id": "MDQ6VXNlcjI5MTU3NTI4", "avatar_url": "https://avatars.githubusercontent.com/u/29157528?v=4", "gravatar_id": "", "url": "https://api.github.com/users/kemu3007", "html_url": "https://github.com/kemu3007", "followers_url": "https://api.github.com/users/kemu3007/followers", "following_url": "https://api.github.com/users/kemu3007/following{/other_user}", "gists_url": "https://api.github.com/users/kemu3007/gists{/gist_id}", "starred_url": "https://api.github.com/users/kemu3007/starred{/owner}{/repo}", "subscriptions_url": "https://api.github.com/users/kemu3007/subscriptions", "organizations_url": "https://api.github.com/users/kemu3007/orgs", "repos_url": "https://api.github.com/users/kemu3007/repos", "events_url": "https://api.github.com/users/kemu3007/events{/privacy}", "received_events_url": "https://api.github.com/users/kemu3007/received_events", "type": "User", "site_admin": false}, "labels": [{"id": 3926670987, "node_id": "LA_kwDOG7qoq87qDD6L", "url": "https://api.github.com/repos/kemu3007/portal/labels/log", "name": "log", "color": "F9846C", "default": false, "description": ""}], "state": "open", "locked": false, "assignee": {"login": "kemu3007", "id": 29157528, "node_id": "MDQ6VXNlcjI5MTU3NTI4", "avatar_url": "https://avatars.githubusercontent.com/u/29157528?v=4", "gravatar_id": "", "url": "https://api.github.com/users/kemu3007", "html_url": "https://github.com/kemu3007", "followers_url": "https://api.github.com/users/kemu3007/followers", "following_url": "https://api.github.com/users/kemu3007/following{/other_user}", "gists_url": "https://api.github.com/users/kemu3007/gists{/gist_id}", "starred_url": "https://api.github.com/users/kemu3007/starred{/owner}{/repo}", "subscriptions_url": "https://api.github.com/users/kemu3007/subscriptions", "organizations_url": "https://api.github.com/users/kemu3007/orgs", "repos_url": "https://api.github.com/users/kemu3007/repos", "events_url": "https://api.github.com/users/kemu3007/events{/privacy}", "received_events_url": "https://api.github.com/users/kemu3007/received_events", "type": "User", "site_admin": false}, "assignees": [{"login": "kemu3007", "id": 29157528, "node_id": "MDQ6VXNlcjI5MTU3NTI4", "avatar_url": "https://avatars.githubusercontent.com/u/29157528?v=4", "gravatar_id": "", "url": "https://api.github.com/users/kemu3007", "html_url": "https://github.com/kemu3007", "followers_url": "https://api.github.com/users/kemu3007/followers", "following_url": "https://api.github.com/users/kemu3007/following{/other_user}", "gists_url": "https://api.github.com/users/kemu3007/gists{/gist_id}", "starred_url": "https://api.github.com/users/kemu3007/starred{/owner}{/repo}", "subscriptions_url": "https://api.github.com/users/kemu3007/subscriptions", "organizations_url": "https://api.github.com/users/kemu3007/orgs", "repos_url": "https://api.github.com/users/kemu3007/repos", "events_url": "https://api.github.com/users/kemu3007/events{/privacy}", "received_events_url": "https://api.github.com/users/kemu3007/received_events", "type": "User", "site_admin": false}], "milestone": null, "comments": 0, "created_at": "2022-05-01T02:02:20Z", "updated_at": "2022-05-01T02:02:21Z", "closed_at": null, "author_association": "OWNER", "active_lock_reason": null, "body": "\r\n## \u4f1a\u5834\r\n\r\n[Zepp Haneda](https://www.zepp.co.jp/hall/haneda/)\r\n\r\n\u5e2d\u306f\u5f8c\u308d\u306e\u65b9\u306eT\u5217\u30014\u5e74\u524d\u306a\u3093\u3070Hatch\u3067\u306f\u7acb\u3061\u898b\u3060\u3063\u305f\u304c\u4eca\u56de\u306f\u30b3\u30ed\u30ca\u4e0b\u3068\u3044\u3046\u3053\u3068\u3082\u3042\u308a\u7740\u5ea7\u3067\u306e\u9451\u8cde\u3002\r\n\r\n![image](https://user-images.githubusercontent.com/29157528/166128919-07bdbe70-a7d9-4589-a6c7-fb556756814b.png)\r\n\r\n## \u30bb\u30c8\u30ea\r\n\r\n###  1\u65e5\u76ee\r\n\r\n\r\n1. \u71b1\u98a8\uff01\u75be\u98a8\uff01\u30b5\u30a4\u30d0\u30b9\u30bf\u30fc\r\n2. \u305d\u306e\u540d\u306f\u30ac\u30a4\u30ad\u30f3\u30b0\u30fb\u30b6\u30fb\u30b0\u30ec\u30fc\u30c8\r\n3. \u98a8\u306e\u30ce\u30fc\u30fb\u30ea\u30d7\u30e9\u30a4\r\n4. \u50b7\u3064\u3044\u305f\u30b8\u30a7\u30e9\u30b7\u30fc\r\n5. \u30a8\u30eb\u30ac\u30a4\u30e0\uff0dTime for L-GAIM\uff0d\r\n6. PATLABOR'99\r\n7. \u30b3\u30f3\u30c7\u30a3\u30b7\u30e7\u30f3\uff65\u30b0\u30ea\u30fc\u30f3\uff5e\u7dca\u6025\u767a\u9032\uff5e\r\n8. Believe yourself Again\r\n9. STAND UP TO THE VICTORY\uff5e\u30c8\u30a5\u30fb\u30b6\u30fb\u30f4\u30a3\u30af\u30c8\u30ea\u30fc\uff5e\r\n10. \u5d50\u306e\u4e2d\u3067\u8f1d\u3044\u3066\r\n11. 10 YEARS AFTER\r\n12. \u30ac\u30f3\u30c0\u30e0\u306b\u611b\u3092\u8fbc\u3081\u3066\r\n13. Z\u30fb\u523b\u3092\u3053\u3048\u3066\r\n14. \u661f\u7a7a\u306eBelieve\r\n15. MEN OF DESTINY\r\n16. YOU GET TO BURNING\r\n17. \u79c1\u3089\u3057\u304f\r\n18. ROSE BUD19. SEVENTH MOON\r\n20. MY SOUL FOR YOU\r\n21. SUBMARINE STREET\r\n22. \u30f4\u30a1\u30fc\u30b8\u30f3\u30b9\u30c8\u30fc\u30ea\u30fc\r\n23. HEY YOU!\r\n24. \u75be\u98a8\u30b6\u30d6\u30f3\u30b0\u30eb\r\n25. \u4e7e\u3044\u305f\u5927\u5730\r\n26. \u30ad\u30f3\u30b0\u30b2\u30a4\u30ca\u30fc\u30fb\u30aa\u30fc\u30d0\u30fc\uff01\r\n27. Can you feel my soul\r\n28. \u795e\u9b42\u5408\u4f53\u30b4\u30fc\u30c0\u30f3\u30ca\u30fc!!\r\n29. \u5922\u8272\u30c1\u30a7\u30a4\u30b5\u30fc\r\n30. \u307f\u3048\u308b\u3060\u308d\u3046 \u30d0\u30a4\u30b9\u30c8\u30f3\u30fb\u30a6\u30a7\u30eb\r\n31. \u30c0\u30f3\u30d0\u30a4\u30f3\u3068\u3076\r\n\r\n### 2\u65e5\u76ee\r\n\r\n1. \u92fc\u306e\u9b42\r\n2. \u9b42\u306e\u30a8\u30f4\u30a9\u30ea\u30e5\u30fc\u30b7\u30e7\u30f3\r\n3. \u6226\u58eb\u3088\u3001\u8d77\u3061\u4e0a\u304c\u308c\uff01\r\n4. Coming Hey you\r\n5. \u92fc\u9244\u306e\u30b3\u30af\u30d4\u30c3\u30c8\r\n6. \u30de\u30b8\u30f3\u30ab\u30a4\u30b6\u30fc\r\n7. CROSS FIGHT\uff01\r\n8. \u3086\u305a\u308c\u306a\u3044\u9858\u3044\r\n9. \u5149\u3068\u5f71\u3092\u62b1\u304d\u3057\u3081\u305f\u307e\u307e\r\n10. All You Need Is Love\r\n11. \u52c7\u8005\u738b\u8a95\u751f\uff01\r\n12. \u305c\u3093\u3076\u52c7\u8005\u304c\u6559\u3048\u3066\u304f\u308c\u305f\r\n13. \u7345\u5b50\u306e\u5973\u738b\uff08\u30ea\u30aa\u30f3\u30fb\u30ec\u30fc\u30cc\uff09-\u30cf\u30a4\u30d1\u30fc\u30fb\u30e2\u30fc\u30c9-\r\n14. \u30dc\u30eb\u30c6\u30b9V\u306e\u6b4c\r\n15. \u5931\u308f\u308c\u305f\u4f1d\u8aac\u3092\u6c42\u3081\u3066\r\n16. \u30d6\u30eb\u30fc\u30fb\u30ec\u30a4\u30f3\r\n17. \u4e0d\u601d\u8b70 CALL ME\r\n18. \u5922\u9280\u6cb3\r\n19. Z\u306e\u30c6\u30fc\u30de\r\n20. \u7a7a\u98db\u3076\u30de\u30b8\u30f3\u30ac\u30fcZ\r\n21. \u308f\u304c\u53cb\u30de\u30b8\u30f3\u30ac\u30fc\uff3a\r\n22. \u30de\u30b8\u30f3\u30ac\u30fc\u30a8\u30f3\u30b8\u30a7\u30eb\u306e\u3046\u305f\r\n23. FIRE WARS\r\n24. \u611f\u3058\u3066Knight\r\n25. Can't Stop\r\n26. HEATS\r\n27. TIME TO COME\r\n28. \u30c0\u30eb\u30bf\u30cb\u30a2\u30b9\u306e\u6b4c\r\n29. \u52c7\u8005\u306f\u30de\u30b8\u30f3\u30ac\u30fc\r\n30. \u71b1\u98a8\uff01\u75be\u98a8\uff01\u30b5\u30a4\u30d0\u30b9\u30bf\u30fc\r\n31.  \u30de\u30b8\u30f3\u30ac\u30fcZ\r\n\r\n## \u6240\u611f\r\n\r\n4\u5e74\u3076\u308a\u306eSRS\u53c2\u6226\u3068\u306a\u3063\u305f\u306e\u3067\u5c11\u3057\u4e0d\u5b89\u304c\u3042\u3063\u305f\u304c\u30014\u5e74\u524d\u3068\u4f55\u3082\u5909\u308f\u3089\u305a\u5b89\u5fc3\u611f\u304c\u3042\u3063\u305f\u3002\r\n\r\n\u4eca\u56de\u3082\u77e5\u3089\u306a\u3044\u66f2\u304c\u8907\u6570\u3042\u3063\u305f\u306e\u3067\u5fa9\u7fd2\u3057\u3066\u6b21\u306b\u5099\u3048\u305f\u3044(\u6b21\u304f\u3089\u3044\u3067\u306f\u58f0\u51fa\u3057\u3067\u304d\u308b\u3088\u3046\u306b\u306a\u3063\u3066\u308b\u3068\u3044\u3044\u306a)\r\n\r\n", "reactions": {"url": "https://api.github.com/repos/kemu3007/portal/issues/39/reactions", "total_count": 0, "+1": 0, "-1": 0, "laugh": 0, "hooray": 0, "confused": 0, "heart": 0, "rocket": 0, "eyes": 0}, "timeline_url": "https://api.github.com/repos/kemu3007/portal/issues/39/timeline", "performed_via_github_app": null}